ccrex/__init__.py
ccrex/ccrex.py
ccrex/run_ccrex.py
ccrex/utils/__init__.py
ccrex/utils/utils.py
ccrex-0.3.3.dist-info/LICENSE
ccrex-0.3.3.dist-info/METADATA
ccrex-0.3.3.dist-info/WHEEL
ccrex-0.3.3.dist-info/top_level.txt
ccrex-0.3.3.dist-info/RECORD
